Metadata-Version: 1.0
Name: barker
Version: 0.1
Summary: Webhook class implementation
Home-page: https://github.com/ethan-nelson/barker
Author: Ethan Nelson
Author-email: git@ethan-nelson.com
License: MIT
Platform: UNKNOWN
